stony/__init__.py
stony/__main__.py
stony/cli.py
stony/client.py
stony/config.py
stony/core.py
stony/templates/article.html
stony/templates/base.html
stony/templates/footer.html
stony/templates/head.html
stony/templates/index.html
stony/templates/macros/render_block.html
stony-0.2.0.dist-info/METADATA
stony-0.2.0.dist-info/WHEEL
stony-0.2.0.dist-info/RECORD
